seabirdfilehandler/__init__.py
seabirdfilehandler/bottlefile.py
seabirdfilehandler/bottlelogfile.py
seabirdfilehandler/cast_borders.py
seabirdfilehandler/cnvfile.py
seabirdfilehandler/ctddata.py
seabirdfilehandler/datafiles.py
seabirdfilehandler/file_collection.py
seabirdfilehandler/geomar_ctd_file_parser.py
seabirdfilehandler/hexdecoder.py
seabirdfilehandler/hexfile.py
seabirdfilehandler/parameter.py
seabirdfilehandler/parameter_mapping.py
seabirdfilehandler/processing_steps.py
seabirdfilehandler/sensor_mapping.toml
seabirdfilehandler/utils.py
seabirdfilehandler/xmlfiles.py
seabirdfilehandler-0.13.2.dist-info/METADATA
seabirdfilehandler-0.13.2.dist-info/WHEEL
seabirdfilehandler-0.13.2.dist-info/licenses/LICENSE
seabirdfilehandler-0.13.2.dist-info/RECORD
