Metadata-Version: 2.4
Name: seabirdfilehandler
Version: 0.13.2
Summary: Library of parsers to interact with SeaBird CTD files.
License-File: LICENSE
Keywords: CTD,parser,seabird,data
Author: Emil Michels
Author-email: <emil.michels@iow.de>
Requires-Python: >=3.12
Classifier: License :: OSI Approved :: GNU General Public License v3 (GPLv3)
Classifier: Development Status :: 3 - Alpha
Classifier: Operating System :: OS Independent
Classifier: Intended Audience :: Science/Research
Classifier: Topic :: Scientific/Engineering :: Oceanography
Classifier: Programming Language :: Python :: 3 :: Only
Classifier: Programming Language :: Python :: 3.12
Classifier: Programming Language :: Python :: 3.13
Classifier: Programming Language :: Python :: 3.14
Provides-Extra: docs
Provides-Extra: test
Requires-Dist: myst-parser (>=4.0.1) ; extra == "docs"
Requires-Dist: pandas (>=2.2.1)
Requires-Dist: parameterized (>=0.9.0) ; extra == "test"
Requires-Dist: pre-commit (>=3.6.2) ; extra == "docs"
Requires-Dist: pre-commit (>=3.6.2) ; extra == "test"
Requires-Dist: pyment (>=0.3.3) ; extra == "docs"
Requires-Dist: pytest (>=8.3.0) ; extra == "test"
Requires-Dist: seabirdscientific (>=2.7.0)
Requires-Dist: sphinx (>=8.2.3) ; extra == "docs"
Requires-Dist: sphinx-autodoc-typehints (>=1.24.1) ; extra == "docs"
Requires-Dist: sphinx-rtd-theme (>=1.3.0) ; extra == "docs"
Requires-Dist: xmltodict (>=0.13.0)
Project-URL: Documentation, https://ctd-software.pages.iow.de/seabirdfilehandler
Project-URL: Homepage, https://ctd-software.pages.iow.de/seabirdfilehandler
Project-URL: Repository, https://git.iow.de/CTD-Software/SeabirdFileHandler
